perplexity_correlations/__init__.py
perplexity_correlations/estimation/__init__.py
perplexity_correlations/estimation/estimation_functions.py
perplexity_correlations/projection/__init__.py
perplexity_correlations/projection/projection_functions.py
tests/__init__.py
tests/test_estimation.py
tests/test_projection.py
perplexity_correlations-0.1.2.dist-info/LICENSE
perplexity_correlations-0.1.2.dist-info/METADATA
perplexity_correlations-0.1.2.dist-info/WHEEL
perplexity_correlations-0.1.2.dist-info/top_level.txt
perplexity_correlations-0.1.2.dist-info/RECORD
