Metadata-Version: 2.1
Name: perplexity_correlations
Version: 0.1.2
Summary: Simple and scalable tools for great pretraining data selection.
Home-page: https://github.com/TristanThrush/perplexity-correlations
Author: Tristan Thrush
Author-email: tthrush@stanford.edu
Project-URL: Documentation, https://tristanthrush.github.io/perplexity-correlations/
Project-URL: Source, https://github.com/TristanThrush/perplexity-correlations
Project-URL: Tracker, https://github.com/TristanThrush/perplexity-correlations/issues
Keywords: AI,artificial intelligence,machine learning,deep learning,research,language models,LLM,pretraining data,data selection,training data,statistics,stats ML
Classifier: Development Status :: 5 - Production/Stable
Classifier: Intended Audience :: Developers
Classifier: Intended Audience :: Education
Classifier: Intended Audience :: Science/Research
Classifier: License :: OSI Approved :: MIT License
Classifier: Operating System :: OS Independent
Classifier: Programming Language :: Python :: 3
Classifier: Topic :: Scientific/Engineering :: Artificial Intelligence
Classifier: Topic :: Scientific/Engineering :: Mathematics
License-File: LICENSE
Requires-Dist: numpy
Provides-Extra: dev
Requires-Dist: flake8>=6.0.0; extra == "dev"
Requires-Dist: pre-commit; extra == "dev"
Requires-Dist: black; extra == "dev"
Requires-Dist: pytest>=7.0.0; extra == "dev"
Requires-Dist: sphinx; extra == "dev"
Requires-Dist: sphinx-rtd-theme; extra == "dev"
Requires-Dist: sphinx-autodoc-typehints; extra == "dev"
Requires-Dist: setuptools; extra == "dev"
Requires-Dist: wheel; extra == "dev"
Requires-Dist: twine; extra == "dev"
